hitl/Uploader.py
hitl/__init__.py
hitl-1.0.dist-info/LICENCE
hitl-1.0.dist-info/METADATA
hitl-1.0.dist-info/WHEEL
hitl-1.0.dist-info/top_level.txt
hitl-1.0.dist-info/RECORD
